CHANGELOG.txt
LICENSE.txt
MANIFEST.in
README.rst
setup.py
ModTkinter/__init__.py
ModTkinter.egg-info/PKG-INFO
ModTkinter.egg-info/SOURCES.txt
ModTkinter.egg-info/dependency_links.txt
ModTkinter.egg-info/requires.txt
ModTkinter.egg-info/top_level.txt