Metadata-Version: 2.1
Name: ModTkinter
Version: 0.0.22
Summary: A Mordernised version of Tkinter, HighDPI for Windows 10, contains some new functions and widgets
Home-page: UNKNOWN
Author: Zin-Lin-Htun
Author-email: zinlinhtun34@gmail.com
License: UNKNOWN
Keywords: tkinter
Platform: UNKNOWN
Classifier: Programming Language :: Python :: 3
Classifier: License :: OSI Approved :: MIT License
Classifier: Operating System :: OS Independent
Requires-Python: >=3.8
